mocap_blender_addons/__init__.py
mocap_blender_addons/better_fbx/__init__.py
mocap_blender_addons/better_fbx/bin/Darwin/fbx-utility
mocap_blender_addons/better_fbx/bin/Darwin/fbx-utility2
mocap_blender_addons/better_fbx/bin/Darwin/fbx-utility3
mocap_blender_addons/better_fbx/bin/Linux/fbx-utility
mocap_blender_addons/better_fbx/bin/Linux/fbx-utility2
mocap_blender_addons/better_fbx/bin/Windows/x64/fbx-utility.exe
mocap_blender_addons/better_fbx/bin/Windows/x86/fbx-utility.exe
mocap_blender_addons/better_fbx/data/.gitkeep
mocap_blender_addons/better_fbx/exporter.py
mocap_blender_addons/better_fbx/gpl-3.0.txt
mocap_blender_addons/better_fbx/importer.py
mocap_blender_operations/__init__.py
mocap_blender_operations/addon_bld/camera_utils.py
mocap_blender_operations/addon_bld/kalman/FBX2glTF
mocap_blender_operations/addon_bld/kalman/blender_error_codes.py
mocap_blender_operations/addon_bld/kalman/calib_to_blender.py
mocap_blender_operations/addon_bld/kalman/combine_blends.py
mocap_blender_operations/addon_bld/kalman/create_rigs.py
mocap_blender_operations/addon_bld/kalman/fbx_export.py
mocap_blender_operations/addon_bld/kalman/kalman_to_blender.py
mocap_blender_operations/addon_bld/kalman/kalman_to_blender_local.py
mocap_blender_operations/addon_bld/kalman/markers_to_blender.py
mocap_blender_operations/addon_bld/kalman/moveai2custom.py
mocap_blender_operations/addon_bld/kalman/props/Ball.blend
mocap_blender_operations/addon_bld/kalman/props/ground_plane.blend
mocap_blender_operations/addon_bld/kalman/props/move_logo.jpeg
mocap_blender_operations/addon_bld/kalman/props/move_logo.png
mocap_blender_operations/addon_bld/kalman/props/move_logo_exp.jpeg
mocap_blender_operations/addon_bld/rig_preparation/constrain_to_urdf.py
mocap_blender_operations/addon_bld/rig_preparation/fbx_to_blend.py
mocap_blender_operations/addon_bld/rig_preparation/render_preview_360.py
mocap_blender_operations/axengine_1766142751_3331378643.py
mocap_blender_operations/kalman_to_blend.py
mocap_blender_operations-2.11.8.dist-info/METADATA
mocap_blender_operations-2.11.8.dist-info/WHEEL
mocap_blender_operations-2.11.8.dist-info/RECORD
