Metadata-Version: 2.1
Name: mocap-blender-operations
Version: 2.11.8
Summary: 
Keywords: MotionOps,Moveai
Author: Move.ai
Author-email: info@move.ai
Requires-Python: >=3.10,<4.0
Classifier: Programming Language :: Python :: 3
Classifier: Programming Language :: Python :: 3.10
Classifier: Programming Language :: Python :: 3.11
Classifier: Programming Language :: Python :: 3.12
Requires-Dist: bpy (>=4.0.0,<5.0.0) ; python_version >= "3.10.dev0" and python_version < "3.11.dev0"
Requires-Dist: bpy (>=4.1.0,<5.0.0) ; python_version >= "3.11.dev0" and python_version < "3.12.dev0"
Requires-Dist: c3d (>=0.5.0,<0.6.0)
Requires-Dist: mocap-base (>=2.0.1,<3.0.0)
Requires-Dist: mocap-blender (>=4.0.5,<5.0.0)
Requires-Dist: mocap_settings (>=1.6.9,<2.0.0)
Requires-Dist: urdf-creator (>=1.1.5,<2.0.0)
